{
  "file": "01.06.2026_12_46_14_79881852495_m19_d138249_6.1780307177.mp3",
  "language": "ru",
  "language_probability": 1,
  "duration_seconds": 97.8,
  "segments": [
    {
      "start": 0.82,
      "end": 8.25,
      "speaker": null,
      "text": "Алло. Дмитрий, добрый день. Меня зовут Влад. Компания МОССПЕНТ. Получу от ВДФ на обратный звонок."
    },
    {
      "start": 12.12,
      "end": 19.34,
      "speaker": null,
      "text": "Так, а что за компания? МОССПЕНТ. Мы занимаемся размещением рекламной вардации."
    },
    {
      "start": 20.63,
      "end": 30.5,
      "speaker": null,
      "text": "Ага. Да я хотел узнать, мне нужны морозильные лари. Знаете, такие есть витринные. Их нужно отклеить."
    },
    {
      "start": 32.56,
      "end": 39.34,
      "speaker": null,
      "text": "Ага, плёнка на них нужна. Да-да-да. Так, мне для этого понадобятся размеры их."
    },
    {
      "start": 39.56,
      "end": 44.02,
      "speaker": null,
      "text": "Угу. Вот, и когда нужно будет это сделать? Когда обклеить нужно?"
    },
    {
      "start": 45.86,
      "end": 49.16,
      "speaker": null,
      "text": "И пока нужно по стоимости разносить, по срокам и коричневым."
    },
    {
      "start": 49.44,
      "end": 54.88,
      "speaker": null,
      "text": "Ну я понял, просто по стоимости, чтобы я корректную цену вам дал, цена же на монтаж ещё есть."
    },
    {
      "start": 55.52,
      "end": 58.2,
      "speaker": null,
      "text": "Вот, а монтаж производится в определённый день, в определённые часы."
    },
    {
      "start": 58.86,
      "end": 61.82,
      "speaker": null,
      "text": "Я понял. Хорошо, куда направить информацию?"
    },
    {
      "start": 63.06,
      "end": 65.54,
      "speaker": null,
      "text": "По этому номеру телефона у вас мессенджеры есть по кому-нибудь?"
    },
    {
      "start": 66.44,
      "end": 67.76,
      "speaker": null,
      "text": "В Макс можно будет, да?"
    },
    {
      "start": 69.62,
      "end": 71.46,
      "speaker": null,
      "text": "Давайте в Макс когда напишу, без проблем."
    },
    {
      "start": 72.34,
      "end": 76.62,
      "speaker": null,
      "text": "Вам плёнка это единственное, что нужно будет с работой или какие-то другие поделки так же интересуют вас?"
    },
    {
      "start": 76.9,
      "end": 79.88,
      "speaker": null,
      "text": "Нет, пока просто холодильники открыть, их мне пять штук."
    },
    {
      "start": 80.85,
      "end": 83.05,
      "speaker": null,
      "text": "Ага, а это они у вас на выставке или объекты торговой точки?"
    },
    {
      "start": 83.81,
      "end": 85.53,
      "speaker": null,
      "text": "Торговой точке, Московские ярмарки."
    },
    {
      "start": 86.75,
      "end": 87.97,
      "speaker": null,
      "text": "Всё, я понял. Хорошо."
    },
    {
      "start": 88.77,
      "end": 92.27,
      "speaker": null,
      "text": "А давайте тогда вам сейчас Макс напишу, вы мне туда уже пропишите."
    },
    {
      "start": 93.21,
      "end": 93.61,
      "speaker": null,
      "text": "Я пишу Павел."
    },
    {
      "start": 94.57,
      "end": 94.73,
      "speaker": null,
      "text": "Спасибо."
    },
    {
      "start": 95.27,
      "end": 95.65,
      "speaker": null,
      "text": "Давайте."
    },
    {
      "start": 95.65,
      "end": 95.93,
      "speaker": null,
      "text": "Субтитры сделал DimaTorzok"
    },
    {
      "start": 95.93,
      "end": 96.31,
      "speaker": null,
      "text": "Субтитры сделал DimaTorzok"
    }
  ]
}