{
  "file": "02.06.2026_15_52_26_79197723711_m33_d136775_f.1780404747.mp3",
  "language": "ru",
  "language_probability": 1,
  "duration_seconds": 311.1,
  "segments": [
    {
      "start": 0.75,
      "end": 31.12,
      "speaker": null,
      "text": "Алло. Алло. Да, Иван, ещё раз добрый день. Еще раз добрый день. Весело у нас, конечно, всё получается. В общем, я вместе с руководством, потому что до того, как я ваши фото не видел, ну, вроде как всё было красиво, а весь ужас, что я увидел то, как вы мне фото прислали, реально лески от... лески даже крупнее, чем полтора миллиметра были, в общем, потом я видел."
    },
    {
      "start": 32.16,
      "end": 46.66,
      "speaker": null,
      "text": "Общался с подрядчиками по монтажу, потому что лески, ну, лески просто всегда монтажники берут вот эти подручные материалы. Я всё напечатал на своё производство, но подручные материалы и всё, что нужно монтажа, это всё делают монтажники. Ну, включая нас, тоже наш монтажник."
    },
    {
      "start": 48.3,
      "end": 57.22,
      "speaker": null,
      "text": "Либо мы всё переделываем, либо всё, как бы, ну, в общем, судом там даже начнёт и так далее."
    },
    {
      "start": 58.96,
      "end": 63.06,
      "speaker": null,
      "text": "Насколько я понял, что сработало, да? Что приехали, переделывали? Просто исчезли?"
    },
    {
      "start": 63.06,
      "end": 69.64,
      "speaker": null,
      "text": "Ну, мы вообще тоже, опять же, ничего не знали. У нас как-то получилось, позвонили опять из аптеки, то есть они нас не предупреждают."
    },
    {
      "start": 69.98,
      "end": 75.9,
      "speaker": null,
      "text": "Нам позвонили из аптеки и сказали, что вот мужчина вчера, который был, он опять пришёл, может прийти и посмотреть, что он там будет делать."
    },
    {
      "start": 76.44,
      "end": 89.27,
      "speaker": null,
      "text": "Вот, мы пришли и, в общем-то, посмотрели. Ну, опять по нашим чутким руководствам, не то, что он был там сейчас лесодоволен, но, как бы, пришёл уже с другой, с новой леской, более тонкой, которая так не видно."
    },
    {
      "start": 90.09,
      "end": 92.29,
      "speaker": null,
      "text": "Вот, она такая, типа, как металлизированная."
    },
    {
      "start": 92.89,
      "end": 97.05,
      "speaker": null,
      "text": "Я вот такую, да, что нужно использовать металлизированную, более тонкую леску."
    },
    {
      "start": 97.05,
      "end": 102.53,
      "speaker": null,
      "text": "Да, вчера они говорили, что это невозможно, сегодня вот он не пришёл с матком и всё там начал фиксировать."
    },
    {
      "start": 103.07,
      "end": 110.07,
      "speaker": null,
      "text": "Ну, в общем-то, под нашим так, руководством и какими-то там комментариями, так, неохотой, но сделал всё вроде как."
    },
    {
      "start": 110.65,
      "end": 114.15,
      "speaker": null,
      "text": "Там просили его, чтобы там ещё освещение, вот эти провода немножко в сторону убрал."
    },
    {
      "start": 114.55,
      "end": 115.49,
      "speaker": null,
      "text": "Вроде то, что я это сделал."
    },
    {
      "start": 115.99,
      "end": 125.73,
      "speaker": null,
      "text": "Ну, в целом, как бы сейчас нас устраивает, то есть мы подняли вот это облако на самый верх, чтобы там было не видно обломок, который там есть."
    },
    {
      "start": 126.89,
      "end": 130.09,
      "speaker": null,
      "text": "Вот, ну, пока висит и вроде как всё хорошо."
    },
    {
      "start": 130.51,
      "end": 133.31,
      "speaker": null,
      "text": "Ну, я не знаю там, насколько мы можем судить непрофессионала, да."
    },
    {
      "start": 133.51,
      "end": 138.74,
      "speaker": null,
      "text": "Да, мы его в любом случае переделаем, потому что это в любом случае считается браком, но это я со своей стороны уже..."
    },
    {
      "start": 139.83,
      "end": 147.57,
      "speaker": null,
      "text": "Ну, да, потому что я уже начал, уже шеф-монтажа своего, то, что там уже вроде как начали смотреть, когда можем приехать и так далее."
    },
    {
      "start": 148.21,
      "end": 149.89,
      "speaker": null,
      "text": "Но раз результаты приехали, исправили."
    },
    {
      "start": 150.05,
      "end": 153.21,
      "speaker": null,
      "text": "В любом случае, это не меняет, конечно, ситуацию, только как они тебя видят."
    },
    {
      "start": 153.21,
      "end": 162.29,
      "speaker": null,
      "text": "В любом случае, хватает чёрный кусок, и я опять же приношу от себя, там, отношусь к компании в целом извинения за такой грубый тон, но, в принципе, как они общались."
    },
    {
      "start": 162.57,
      "end": 162.87,
      "speaker": null,
      "text": "Спасибо."
    },
    {
      "start": 164.31,
      "end": 169.12,
      "speaker": null,
      "text": "Представляю, у меня клиенты тоже бывают, которые живут вообще."
    },
    {
      "start": 170.04,
      "end": 180.46,
      "speaker": null,
      "text": "Ну, да, просто проблема в том, что, как бы, если бы они сразу вчера сделали, там, ладно, с какими-то пинками и агрессией, уже бы это всё хорошо было, и сейчас бы это висело."
    },
    {
      "start": 181.16,
      "end": 186.42,
      "speaker": null,
      "text": "Мне кажется, им бы не пришлось приезжать опять это всё переделывать и по новой там всё перевешивать."
    },
    {
      "start": 186.42,
      "end": 187.94,
      "speaker": null,
      "text": "Да, я вас прекрасно понимаю."
    },
    {
      "start": 188.12,
      "end": 192.34,
      "speaker": null,
      "text": "Я, в принципе, тоже сам объяснял, что если бы всё было нормально, то и не нужно было бы ездить."
    },
    {
      "start": 192.98,
      "end": 198.7,
      "speaker": null,
      "text": "Да, это просто лишнее время их и наши тратите, как бы, в бессмысленном действии, да."
    },
    {
      "start": 201.07,
      "end": 203.21,
      "speaker": null,
      "text": "Спасибо большое, что у меня позвонили не читали."
    },
    {
      "start": 204.29,
      "end": 205.49,
      "speaker": null,
      "text": "Давайте тогда таким образом."
    },
    {
      "start": 205.69,
      "end": 205.73,
      "speaker": null,
      "text": "Спасибо."
    },
    {
      "start": 206.41,
      "end": 212.91,
      "speaker": null,
      "text": "В следующий раз я, в принципе, на все наши с вами работы не буду привлекать каких-то подрядчиков по монтажам."
    },
    {
      "start": 213.27,
      "end": 217.55,
      "speaker": null,
      "text": "Если вдруг прям я не буду успевать с нашими монтажниками, давайте я вам лучше прям поговорить,"
    },
    {
      "start": 217.73,
      "end": 222.07,
      "speaker": null,
      "text": "либо, может, кого-то другого порекомендую, кто там получше и так далее."
    },
    {
      "start": 222.81,
      "end": 228.49,
      "speaker": null,
      "text": "Надеюсь, что тоже такого каких-то резких таких не будет, что там прям за неделю и всё, или растрел."
    },
    {
      "start": 229.57,
      "end": 230.33,
      "speaker": null,
      "text": "Такого не было."
    },
    {
      "start": 232.49,
      "end": 238.83,
      "speaker": null,
      "text": "Смотрите, там ещё от аптеки мне прислали телефон, он говорил про неоновую вот эту подсветку."
    },
    {
      "start": 239.83,
      "end": 240.89,
      "speaker": null,
      "text": "Я вам тогда сейчас его направлю."
    },
    {
      "start": 241.67,
      "end": 247.51,
      "speaker": null,
      "text": "А ещё подскажите, пожалуйста, какой-то демонтаж в последующем, а ты как вообще нам с этим действовать, если что?"
    },
    {
      "start": 247.79,
      "end": 254.09,
      "speaker": null,
      "text": "Ну, это понятно, что не ближайшего месяца, где-то три месяца у нас планируется точно, что это будет стоять."
    },
    {
      "start": 254.49,
      "end": 256.99,
      "speaker": null,
      "text": "А в дальнейшем что нам делать, каким образом поступать?"
    },
    {
      "start": 256.99,
      "end": 259.23,
      "speaker": null,
      "text": "В целом, также просто звоните, пишите."
    },
    {
      "start": 259.55,
      "end": 263.53,
      "speaker": null,
      "text": "Я вам сформирую счёт, он, естественно, будет меньше, чем за монтаж, на то, что нам нужно забрать."
    },
    {
      "start": 264.05,
      "end": 269.27,
      "speaker": null,
      "text": "Ну и, собственно, там уже мои ребята поедут, там ничего такого прям сверхъестественного нет."
    },
    {
      "start": 269.99,
      "end": 277.99,
      "speaker": null,
      "text": "В целом, если хотите сэкономить, допустим, ну хотя, опять же, лишняя работа для вас, можно и самому сделать."
    },
    {
      "start": 278.43,
      "end": 286.79,
      "speaker": null,
      "text": "Ну, кстати, кубы я сделал прям, но кубы отдельно на производстве тоже обратил внимание, они прям очень крутые, очень высококачественные."
    },
    {
      "start": 286.79,
      "end": 290.11,
      "speaker": null,
      "text": "Вы сможете потом использовать их и на выставках, и можете поставить."
    },
    {
      "start": 290.11,
      "end": 291.67,
      "speaker": null,
      "text": "Ну, видели, они прям..."
    },
    {
      "start": 291.67,
      "end": 293.25,
      "speaker": null,
      "text": "Да, безусловно, это так."
    },
    {
      "start": 293.53,
      "end": 293.87,
      "speaker": null,
      "text": "Хорошо."
    },
    {
      "start": 294.39,
      "end": 295.31,
      "speaker": null,
      "text": "Спасибо вам огромное."
    },
    {
      "start": 295.33,
      "end": 298.09,
      "speaker": null,
      "text": "Ну, а опять остальные пвхашки после демонтажа, опять же, я вам отвезу."
    },
    {
      "start": 298.17,
      "end": 299.73,
      "speaker": null,
      "text": "Хотите выкиньте, хотите где-то использовать."
    },
    {
      "start": 299.93,
      "end": 301.75,
      "speaker": null,
      "text": "Хоть на стену можно тут в корнице прилепить."
    },
    {
      "start": 301.75,
      "end": 303.45,
      "speaker": null,
      "text": "Хорошо, будем на седу."
    },
    {
      "start": 303.63,
      "end": 304.15,
      "speaker": null,
      "text": "Хорошо, спасибо."
    },
    {
      "start": 304.69,
      "end": 305.21,
      "speaker": null,
      "text": "До свидания, Никита."
    },
    {
      "start": 305.45,
      "end": 306.03,
      "speaker": null,
      "text": "Да, хорошо."
    },
    {
      "start": 306.33,
      "end": 306.89,
      "speaker": null,
      "text": "До свидания."
    },
    {
      "start": 306.99,
      "end": 308.19,
      "speaker": null,
      "text": "Уже все хорошо закончилось."
    },
    {
      "start": 308.55,
      "end": 309.03,
      "speaker": null,
      "text": "Да, до свидания."
    },
    {
      "start": 309.65,
      "end": 310.35,
      "speaker": null,
      "text": "До свидания."
    }
  ]
}