{
  "file": "03.06.2026_17_08_36_79197723711_m33_d135867_3.1780495717.mp3",
  "language": "ru",
  "language_probability": 1,
  "duration_seconds": 129.6,
  "segments": [
    {
      "start": 0.59,
      "end": 30.92,
      "speaker": null,
      "text": "Алло. Алло, да, Никита, звонили? Да, Иван, звонил я по поводу как раз замены этого неонного освещения. Сейчас уже в процессе с вами поговорили, сказал коллегам и мне в голову это не пришло по поводу того, что для того, чтобы поменять там эту подсветку, это же нужно будет ещё и витрину получается разбирать. Он может подлезть туда так, чтобы ничего там, так скажем, не повредить или хотя бы никогда."
    },
    {
      "start": 31.72,
      "end": 48.02,
      "speaker": null,
      "text": "В сторону не убрать. Вот такой вот вопрос. Наружу у них витрине открывается, то есть это только изнутри, вот как монтировали, в принципе там это всё опять по новой проходить."
    },
    {
      "start": 50.86,
      "end": 57.67,
      "speaker": null,
      "text": "Так, ну тогда сейчас я буду узнавать у этого мужика, который неон хочет поменять."
    },
    {
      "start": 58.36,
      "end": 65.76,
      "speaker": null,
      "text": "Да, нам тогда нужно будет как-то это всё с вами решить в какой-то момент, чтобы и в аптеке предупредить."
    },
    {
      "start": 66.26,
      "end": 74.52,
      "speaker": null,
      "text": "Когда придётся человеку, может быть, это всё как-то вместе организовать сразу, чтобы, может быть, с вашей стороны был как-то представитель."
    },
    {
      "start": 75.61,
      "end": 80.25,
      "speaker": null,
      "text": "От нас мы подойдём, соответственно. Вот. И этот человек, который неон будет там менять."
    },
    {
      "start": 81.85,
      "end": 88.09,
      "speaker": null,
      "text": "Я понял. Просто это будет, да, ещё дополнительно денег стоять, разборка-разборка заново."
    },
    {
      "start": 88.98,
      "end": 93.18,
      "speaker": null,
      "text": "У меня монтаж, которые бесплатно не согласятся, они так много ещё у меня сейчас делают."
    },
    {
      "start": 94.38,
      "end": 100.99,
      "speaker": null,
      "text": "Ну, зачем я, конечно, не плачу, но уже там практически в минус, так что нужно будет как-то решить этот вопрос."
    },
    {
      "start": 102.3,
      "end": 106.66,
      "speaker": null,
      "text": "Ну, давайте посмотрим. Для начала в любом случае ему надо будет подъехать и всё это, да, как-то смотреть."
    },
    {
      "start": 106.92,
      "end": 110.62,
      "speaker": null,
      "text": "И может быть, всё-таки получится там как-то другому это сделать."
    },
    {
      "start": 110.98,
      "end": 117.48,
      "speaker": null,
      "text": "Но это только можно сказать человеку, который будет, собственно, вот эту немного последовательную менять, что ему там для этого понадобится."
    },
    {
      "start": 119.02,
      "end": 121.26,
      "speaker": null,
      "text": "Ладно, всё, хорошо. Сейчас я так думаю."
    },
    {
      "start": 121.42,
      "end": 125.54,
      "speaker": null,
      "text": "Видео я вам сейчас загружу, вот в телеграмму уже кидаю буквально, наверное, через минуту будет у вас."
    },
    {
      "start": 125.68,
      "end": 126.08,
      "speaker": null,
      "text": "Ну, спасибо."
    },
    {
      "start": 127.22,
      "end": 128.12,
      "speaker": null,
      "text": "Через антож посуда."
    },
    {
      "start": 128.28,
      "end": 128.62,
      "speaker": null,
      "text": "До свидания."
    },
    {
      "start": 129.16,
      "end": 129.52,
      "speaker": null,
      "text": "До свидания."
    }
  ]
}