{
  "file": "12.03.2026_14_25_30_79920055480_m27_d128097_e.1773314730.mp3",
  "language": "ru",
  "language_probability": 1,
  "duration_seconds": 85.5,
  "segments": [
    {
      "start": 0.37,
      "end": 31.52,
      "speaker": null,
      "text": "Алло. Анастасия, добрый день, это Валентин, компания «Мастанд». Ага, здравствуйте. Здравствуйте. Скажите, пожалуйста, у вас мероприятие, которое планируется, вы стенды планируете единоразово разместить или в дальнейшем их использовать на мероприятиях? В аренду. А, это в аренду? Угу. Все хорошо, я просто по поводу аренды не увидел информацию. Угу."
    },
    {
      "start": 32.19,
      "end": 40.19,
      "speaker": null,
      "text": "Да, все хорошо тогда в таком случае вопросов нет. А мероприятие у вас в каком формате будет проходить? Это выставка…"
    },
    {
      "start": 41.19,
      "end": 47.36,
      "speaker": null,
      "text": "Конференция это будет. А, конференция. Полиграфия сувенирная продукция, может потребоваться?"
    },
    {
      "start": 48.26,
      "end": 52.66,
      "speaker": null,
      "text": "Да, мы ведём расчёты. А вы кроме прослов ещё занимаетесь чем-то?"
    },
    {
      "start": 52.98,
      "end": 57.02,
      "speaker": null,
      "text": "Да, да, у нас полиграфия сувенирная продукция, выставочное оборудование."
    },
    {
      "start": 57.25,
      "end": 68.9,
      "speaker": null,
      "text": "Ага. Я тогда вам тоже могу направить наш объём. У нас там производство и бейджей, и блокнотов-то не блокнотов разного."
    },
    {
      "start": 69.68,
      "end": 75.3,
      "speaker": null,
      "text": "Угу. Хорошо. Будет замечательно. Угу, ну все тогда. Направлю."
    },
    {
      "start": 76.02,
      "end": 81.77,
      "speaker": null,
      "text": "Все хорошо, я вот всегда понял. Сейчас я рассчитаю стоимость и напишу вам."
    },
    {
      "start": 81.77,
      "end": 84.45,
      "speaker": null,
      "text": "Спасибо. До свидания."
    },
    {
      "start": 84.45,
      "end": 84.61,
      "speaker": null,
      "text": "До свидания."
    },
    {
      "start": 84.89,
      "end": 85.11,
      "speaker": null,
      "text": "Продолжение следует..."
    }
  ]
}