{
  "file": "14.04.2026_10_12_42_79966810830_m39_d132705_b.1776150762.mp3",
  "language": "ru",
  "language_probability": 1,
  "duration_seconds": 129.9,
  "segments": [
    {
      "start": 1.01,
      "end": 7.24,
      "speaker": null,
      "text": "Алло. Да, Максим, у меня просто что-то вы пропали в моменте, пытался вам позвонить, а вы тоже мне звонили."
    },
    {
      "start": 8.24,
      "end": 15.32,
      "speaker": null,
      "text": "Угу, угу, да, смотрите, вопрос такой, что я могу и сам в принципе подъехать забрать."
    },
    {
      "start": 17.36,
      "end": 21.04,
      "speaker": null,
      "text": "Вызов Мартеновская 35А, это недалеко от метро Новогирево."
    },
    {
      "start": 24.3,
      "end": 27.96,
      "speaker": null,
      "text": "Хорошо, сориентируйте по стоимости, сколько это примерно будет?"
    },
    {
      "start": 27.96,
      "end": 46.64,
      "speaker": null,
      "text": "Так, одну секунду. Так, конструкция получается 100 на 200 – 4 тысячи рублей, это конструкция плюс сумка и печать баннера у нас получается 2 800, если мы сегодня печатаем."
    },
    {
      "start": 47.68,
      "end": 53.46,
      "speaker": null,
      "text": "Угу. Итого под ключ это будет 6 800. Отлично."
    },
    {
      "start": 53.46,
      "end": 57.5,
      "speaker": null,
      "text": "Это печать, конструкция и сумка для переноски. Размеры 100 на 200."
    },
    {
      "start": 58.47,
      "end": 63.71,
      "speaker": null,
      "text": "Отлично, хорошо. Могу я тогда попросить 2 рулапа?"
    },
    {
      "start": 64.09,
      "end": 65.87,
      "speaker": null,
      "text": "Угу. Да, конечно, два рулапа."
    },
    {
      "start": 66.03,
      "end": 68.66,
      "speaker": null,
      "text": "Вот. А если 3?"
    },
    {
      "start": 69.22,
      "end": 70.6,
      "speaker": null,
      "text": "Это 3 макеты?"
    },
    {
      "start": 70.6,
      "end": 77.56,
      "speaker": null,
      "text": "Тоже возможно. В принципе, говорить с производством возможно. Если у вас макеты светлые, вообще тогда проблем не будет."
    },
    {
      "start": 78.77,
      "end": 83.19,
      "speaker": null,
      "text": "Да, они цветные, светлые, да, не черные в общем-то."
    },
    {
      "start": 83.63,
      "end": 88.31,
      "speaker": null,
      "text": "Угу. Подскажите мне, пожалуйста, какой канал передачи макетов?"
    },
    {
      "start": 88.31,
      "end": 94.03,
      "speaker": null,
      "text": "А я вам сейчас напишу по номеру телефона, да, вот как раз спрашивал. Вам куда будет написать? В Телеграм? В Макс?"
    },
    {
      "start": 94.73,
      "end": 96.19,
      "speaker": null,
      "text": "Можно в Макс, пожалуйста."
    },
    {
      "start": 96.51,
      "end": 98.4,
      "speaker": null,
      "text": "Да, конечно, здесь."
    },
    {
      "start": 99.52,
      "end": 104.54,
      "speaker": null,
      "text": "Да, хорошо. А, единственное, что у меня для того, чтобы тоже оформить, подскажите сферу мероприятия."
    },
    {
      "start": 107.23,
      "end": 110.51,
      "speaker": null,
      "text": "Это конференция медицинская, старш-медицина."
    },
    {
      "start": 111.19,
      "end": 113.11,
      "speaker": null,
      "text": "Угу. Медицина."
    },
    {
      "start": 114.8,
      "end": 123.16,
      "speaker": null,
      "text": "Все? Я понял. Хорошо. Тогда в течение двух минут вам по этому номеру телефона напишу информацию еще раз, фото примера и там продолжим общение."
    },
    {
      "start": 123.84,
      "end": 125.3,
      "speaker": null,
      "text": "Угу. Хорошо. Спасибо огромное."
    },
    {
      "start": 125.38,
      "end": 127.06,
      "speaker": null,
      "text": "Да. Хорошего дня. До свидания."
    },
    {
      "start": 127.5,
      "end": 128.08,
      "speaker": null,
      "text": "До свидания."
    }
  ]
}