{
  "file": "17.03.2026_15_41_31_79035433989_m31_d127921_b.1773751292.mp3",
  "language": "ru",
  "language_probability": 1,
  "duration_seconds": 161.3,
  "segments": [
    {
      "start": 2.93,
      "end": 7.63,
      "speaker": null,
      "text": "Здравствуйте, Илья. Это Валерий из моего стенд. Ранее общались с вами по поводу стендов."
    },
    {
      "start": 7.67,
      "end": 9.51,
      "speaker": null,
      "text": "Добрый день."
    },
    {
      "start": 10.29,
      "end": 12.15,
      "speaker": null,
      "text": "Да, вот что жду от вас ответ?"
    },
    {
      "start": 14.86,
      "end": 16.5,
      "speaker": null,
      "text": "Напомните, на чём мы с вами остановились."
    },
    {
      "start": 16.94,
      "end": 21.48,
      "speaker": null,
      "text": "Ну, вы хотели собрать сами брусовой пресс-вол, то есть брусовой стенд."
    },
    {
      "start": 22.22,
      "end": 25.72,
      "speaker": null,
      "text": "Да, но я объяснила, что там это достаточно сложно будет сделать."
    },
    {
      "start": 27.42,
      "end": 30.02,
      "speaker": null,
      "text": "Почему? У вас же других вариантов просто нет?"
    },
    {
      "start": 30.88,
      "end": 41.18,
      "speaker": null,
      "text": "Ну, других вариантов нет, либо сделать просто отдельно, то есть обычный стандартный мобильный стенд и на него не крепить ничего."
    },
    {
      "start": 41.38,
      "end": 46.42,
      "speaker": null,
      "text": "Потому что в целом мобильные, просто обычные мобильные стенды, они для того осознаны, что они лёгкие."
    },
    {
      "start": 46.96,
      "end": 50.0,
      "speaker": null,
      "text": "А если стенд лёгкий и 60 килограмм он не выдержит."
    },
    {
      "start": 50.26,
      "end": 54.28,
      "speaker": null,
      "text": "Почему это нам нужен, если он не выдержит?"
    },
    {
      "start": 55.16,
      "end": 60.24,
      "speaker": null,
      "text": "Тогда это получается не мобильный стенд, его перевозить нельзя, невозможно."
    },
    {
      "start": 60.56,
      "end": 60.82,
      "speaker": null,
      "text": "Почему?"
    },
    {
      "start": 61.78,
      "end": 70.86,
      "speaker": null,
      "text": "Потому что он не мобильный, он не складывается, ну то есть его можно только один раз собрать, его можно разобрать ещё и потом это утилизировать."
    },
    {
      "start": 71.16,
      "end": 72.68,
      "speaker": null,
      "text": "То есть это вот такая вот история."
    },
    {
      "start": 72.94,
      "end": 75.16,
      "speaker": null,
      "text": "Он потом они собирается? А по какой причине?"
    },
    {
      "start": 76.3,
      "end": 85.2,
      "speaker": null,
      "text": "Ну потому что, смотрите, вы палки, вы их собрали в стенд, потом вы их просто не сможете использовать, потому что палки-то уже использованные."
    },
    {
      "start": 85.2,
      "end": 88.8,
      "speaker": null,
      "text": "Чтобы собрать его заново, нужны новые палки."
    },
    {
      "start": 90.42,
      "end": 90.98,
      "speaker": null,
      "text": "Брус новый."
    },
    {
      "start": 90.98,
      "end": 93.32,
      "speaker": null,
      "text": "Вот тут не очень понимаю, почему нужны новые брусы."
    },
    {
      "start": 93.48,
      "end": 97.07,
      "speaker": null,
      "text": "Я понимаю, там крепление просто снимается и ставится назад."
    },
    {
      "start": 97.63,
      "end": 98.81,
      "speaker": null,
      "text": "С помощью чего они крепятся?"
    },
    {
      "start": 99.11,
      "end": 100.49,
      "speaker": null,
      "text": "Нет, смотрите, там дерево."
    },
    {
      "start": 100.61,
      "end": 102.35,
      "speaker": null,
      "text": "То есть брус это деревянные палки."
    },
    {
      "start": 104.09,
      "end": 109.13,
      "speaker": null,
      "text": "Они крепятся за счёт, естественно, всяких этих саморезов."
    },
    {
      "start": 109.27,
      "end": 111.43,
      "speaker": null,
      "text": "То есть это делает наш монтажник."
    },
    {
      "start": 111.61,
      "end": 115.87,
      "speaker": null,
      "text": "Он определённо под себя пилит определённые размеры вот этих палок."
    },
    {
      "start": 116.65,
      "end": 118.85,
      "speaker": null,
      "text": "Выезжает на локацию, на локацию ставит."
    },
    {
      "start": 118.85,
      "end": 121.81,
      "speaker": null,
      "text": "Если нужно какое-то утяжеление, то он ставит утяжелители."
    },
    {
      "start": 122.03,
      "end": 124.67,
      "speaker": null,
      "text": "Утяжелители – это зачастую мешки с песком."
    },
    {
      "start": 124.97,
      "end": 125.93,
      "speaker": null,
      "text": "Это зачастую так."
    },
    {
      "start": 126.37,
      "end": 129.57,
      "speaker": null,
      "text": "То есть утяжеляют сам стенд для того, чтобы он выдержал."
    },
    {
      "start": 130.03,
      "end": 136.17,
      "speaker": null,
      "text": "Но потом, грубо говоря, эти палки, когда вы их разберёте, они будут уже использованные."
    },
    {
      "start": 136.31,
      "end": 138.13,
      "speaker": null,
      "text": "Дерево ещё раз собрать не получится."
    },
    {
      "start": 138.65,
      "end": 140.47,
      "speaker": null,
      "text": "То есть оно на один раз в целом."
    },
    {
      "start": 141.72,
      "end": 142.46,
      "speaker": null,
      "text": "Я понял."
    },
    {
      "start": 143.16,
      "end": 145.24,
      "speaker": null,
      "text": "Но получается, что нам не подходит никакой вариант?"
    },
    {
      "start": 145.24,
      "end": 147.36,
      "speaker": null,
      "text": "Ну, получается так."
    },
    {
      "start": 147.46,
      "end": 150.14,
      "speaker": null,
      "text": "Тогда не могу вам больше ничего, к сожалению, предложить."
    },
    {
      "start": 150.54,
      "end": 151.74,
      "speaker": null,
      "text": "Понял вас за..."
    },
    {
      "start": 152.45,
      "end": 153.34,
      "speaker": null,
      "text": "Ну да, к сожалению."
    },
    {
      "start": 153.64,
      "end": 154.52,
      "speaker": null,
      "text": "Спасибо, что ты говоришь."
    },
    {
      "start": 155.14,
      "end": 155.6,
      "speaker": null,
      "text": "Да-да."
    },
    {
      "start": 155.7,
      "end": 156.76,
      "speaker": null,
      "text": "Вам тогда всего доброго."
    },
    {
      "start": 157.0,
      "end": 157.52,
      "speaker": null,
      "text": "До свидания."
    },
    {
      "start": 158.12,
      "end": 158.62,
      "speaker": null,
      "text": "Спасибо."
    },
    {
      "start": 158.78,
      "end": 159.18,
      "speaker": null,
      "text": "До свидания."
    }
  ]
}