{
  "file": "20.04.2026_15_58_30_+79778831588_m37_d133583_8.1776689909.mp3",
  "language": "ru",
  "language_probability": 1,
  "duration_seconds": 285.5,
  "segments": [
    {
      "start": 0.82,
      "end": 1.44,
      "speaker": null,
      "text": "Алло."
    },
    {
      "start": 2.31,
      "end": 7.39,
      "speaker": null,
      "text": "Алексей, добрый день! Это Екатерина, компания Мастент. Отставили на заявку на сайте. Чем могу помочь?"
    },
    {
      "start": 9.01,
      "end": 21.11,
      "speaker": null,
      "text": "Хотел бы, чтобы вы меня сориентировали по стоимости на Roll Up Classic и вообще как у вас происходит. Размер метр на два."
    },
    {
      "start": 22.71,
      "end": 25.15,
      "speaker": null,
      "text": "Так, одна штука вам нужна или тираж какой-то?"
    },
    {
      "start": 26.24,
      "end": 27.06,
      "speaker": null,
      "text": "Пока одна."
    },
    {
      "start": 28.9,
      "end": 37.24,
      "speaker": null,
      "text": "Стоимость конструкции 4000 рублей, это роллап классический с ножками. Печать на баннере 1900. То есть 5900 получается эта конструкция 200 тысяча."
    },
    {
      "start": 37.36,
      "end": 41.56,
      "speaker": null,
      "text": "Сумка идёт в комплекте, в который подставляется Roll Up."
    },
    {
      "start": 42.28,
      "end": 46.32,
      "speaker": null,
      "text": "А когда вам нужен дизайн макет? Как у вас с этим делом стоит?"
    },
    {
      "start": 47.28,
      "end": 59.5,
      "speaker": null,
      "text": "Ну, если вам нужно полностью с нуля разработать макет, но при этом предоставить на материалы, брит заполнить и картинки, если нужно какие-то расположить, логотипы, то 2000 рублей разработка."
    },
    {
      "start": 59.5,
      "end": 67.14,
      "speaker": null,
      "text": "Если чего-то нет и что-то нужно рисовать от руки, то 3000 в зависимости от того, чего нет и что нужно будет делать. То есть от сложности макета."
    },
    {
      "start": 68.27,
      "end": 79.16,
      "speaker": null,
      "text": "Ну вот есть сайт, на нём есть вся информация, есть фотография, есть логотип. Ну а там дальше уже зависит от фантазии вашего дизайнера, как он это всё делает?"
    },
    {
      "start": 79.72,
      "end": 88.72,
      "speaker": null,
      "text": "У нас там дизайнер не работает, к сожалению, потому что у нас дизайнер штатный, он креативом не занимается. У него нет времени на это, потому что большое количество задач."
    },
    {
      "start": 89.12,
      "end": 96.84,
      "speaker": null,
      "text": "То есть я вам могу направить бриф, вы его заполните, как хотите видеть макет, то есть как что расположить. И соответственно исходя из этого дизайнер уже делает."
    },
    {
      "start": 97.5,
      "end": 104.52,
      "speaker": null,
      "text": "Потому что если делать креатив, во-первых, это очень долго по времени будет, но и дороже. Креатив у нас от 10 тысяч рублей."
    },
    {
      "start": 106.13,
      "end": 108.33,
      "speaker": null,
      "text": "Ну там креативить ещё не надо особо."
    },
    {
      "start": 108.77,
      "end": 113.75,
      "speaker": null,
      "text": "Ну вы же говорите, что пусть он сам разберётся, как будет делать, лучше будет. Я имею в виду вот это."
    },
    {
      "start": 114.15,
      "end": 121.51,
      "speaker": null,
      "text": "Я говорю о том, что информация вводная есть, а как это оформить – это уже на его усмотрение."
    },
    {
      "start": 121.63,
      "end": 127.39,
      "speaker": null,
      "text": "Если у вас есть какие-то постановки или наработки, то тогда можно их использовать."
    },
    {
      "start": 127.39,
      "end": 129.15,
      "speaker": null,
      "text": "То есть не обязательно там что-то задавать."
    },
    {
      "start": 129.17,
      "end": 133.27,
      "speaker": null,
      "text": "Я про это вам и говорю. Нам в любом случае нужно понимание, как выходить и что расположить."
    },
    {
      "start": 133.39,
      "end": 142.45,
      "speaker": null,
      "text": "То есть в каком углу, например, логотип, грубо говоря, где названия, какие картинки и куда их расположить, какой фон основной – вот это нужна информация от вас."
    },
    {
      "start": 143.56,
      "end": 147.28,
      "speaker": null,
      "text": "Ну, не проблема. Давайте я предоставлю всё, что нужно."
    },
    {
      "start": 148.0,
      "end": 150.06,
      "speaker": null,
      "text": "Хорошо, не проблема. А когда вам нужен РЛАП?"
    },
    {
      "start": 151.8,
      "end": 152.98,
      "speaker": null,
      "text": "Есть дата какая-то?"
    },
    {
      "start": 153.78,
      "end": 153.94,
      "speaker": null,
      "text": "А?"
    },
    {
      "start": 154.54,
      "end": 156.3,
      "speaker": null,
      "text": "Дата есть, когда вам нужен РЛАП?"
    },
    {
      "start": 156.56,
      "end": 158.66,
      "speaker": null,
      "text": "А какие сроки у вас производства?"
    },
    {
      "start": 158.66,
      "end": 163.5,
      "speaker": null,
      "text": "Вообще, стандартный срок – один рабочий день с момента согласования макета внесения оплаты."
    },
    {
      "start": 163.76,
      "end": 167.98,
      "speaker": null,
      "text": "Я просто уточняю, у вас какое-то мероприятие или для чего это потребуется?"
    },
    {
      "start": 168.12,
      "end": 174.28,
      "speaker": null,
      "text": "То 1 мая нужно успеть нам его подготовить. Мы планируем участие в выставке."
    },
    {
      "start": 174.92,
      "end": 175.76,
      "speaker": null,
      "text": "Угу, поняла."
    },
    {
      "start": 175.76,
      "end": 177.76,
      "speaker": null,
      "text": "Хорошо, да? Без проблем есть."
    },
    {
      "start": 178.44,
      "end": 184.82,
      "speaker": null,
      "text": "Скажите еще, пожалуйста, а можете вы еще сделать какие-то рекламные листовки формата А4?"
    },
    {
      "start": 185.9,
      "end": 194.4,
      "speaker": null,
      "text": "Мало того, чтобы люди приходили на стенд, смотрели эту информацию на РЛАПе, чтобы им еще что-то в руки вручить какой-то раздаточный материал."
    },
    {
      "start": 194.44,
      "end": 198.04,
      "speaker": null,
      "text": "Да, понимаю. Я вот как раз хотела у вас спросить. Конечно, можно без проблем."
    },
    {
      "start": 198.04,
      "end": 204.42,
      "speaker": null,
      "text": "А подскажите, у вас получается на стенде вот будет только РЛАП и раздаточная продукция, да?"
    },
    {
      "start": 205.27,
      "end": 211.29,
      "speaker": null,
      "text": "Просто РЛАП метр на два какой-то, ну он маловатый для стенда как такового."
    },
    {
      "start": 211.71,
      "end": 221.19,
      "speaker": null,
      "text": "Ну там у нас не то чтобы прям стенд, у нас там уголочек будет в общем стенде выделен для наших задач."
    },
    {
      "start": 221.45,
      "end": 223.71,
      "speaker": null,
      "text": "Поэтому для нас этого будет достаточно."
    },
    {
      "start": 224.07,
      "end": 225.13,
      "speaker": null,
      "text": "Достаточно. Поняла."
    },
    {
      "start": 225.13,
      "end": 229.45,
      "speaker": null,
      "text": "Хорошо, без проблем. Да, макет если нужно тоже для листовок сделаем."
    },
    {
      "start": 229.59,
      "end": 233.43,
      "speaker": null,
      "text": "Точно так же необходимо будет бриф, чтобы вы заполнили что-то разместить на листовках."
    },
    {
      "start": 233.95,
      "end": 235.21,
      "speaker": null,
      "text": "И без проблем все сделаем, конечно."
    },
    {
      "start": 236.76,
      "end": 238.9,
      "speaker": null,
      "text": "Ну хорошо, без проблем все сделаете, точно?"
    },
    {
      "start": 240.51,
      "end": 241.31,
      "speaker": null,
      "text": "Да, без проблем."
    },
    {
      "start": 242.67,
      "end": 245.41,
      "speaker": null,
      "text": "Замечательно. Куда направить информацию в день?"
    },
    {
      "start": 245.59,
      "end": 250.3,
      "speaker": null,
      "text": "Я могу вам на этот номер телефона. Есть у вас Telegram по этому номеру телефона?"
    },
    {
      "start": 250.72,
      "end": 251.36,
      "speaker": null,
      "text": "Пока есть."
    },
    {
      "start": 251.36,
      "end": 259.66,
      "speaker": null,
      "text": "Давайте, давайте я вам напишу на Telegram и ну если что можем через почту. Как вам удобно? Мне без разницы. Главное чтобы вам было удобно информацию отправлять."
    },
    {
      "start": 259.66,
      "end": 266.16,
      "speaker": null,
      "text": "Просто по файлам можно если что через почту обменяться, потому что Telegram не всегда корректно все подгружаются."
    },
    {
      "start": 266.68,
      "end": 269.7,
      "speaker": null,
      "text": "Ну я в любом случае вам сейчас напишу на Telegram, дальше продолжим общение."
    },
    {
      "start": 269.96,
      "end": 273.36,
      "speaker": null,
      "text": "Если что через почту каким-то файлом мы обменяемся."
    },
    {
      "start": 274.0,
      "end": 274.58,
      "speaker": null,
      "text": "Тоже не вопрос."
    },
    {
      "start": 275.99,
      "end": 276.29,
      "speaker": null,
      "text": "Хорошо?"
    },
    {
      "start": 276.85,
      "end": 277.93,
      "speaker": null,
      "text": "Без проблем."
    },
    {
      "start": 278.65,
      "end": 280.97,
      "speaker": null,
      "text": "Все, хорошо. Я сейчас напишу буквально в рамках 5 минут."
    },
    {
      "start": 281.84,
      "end": 282.68,
      "speaker": null,
      "text": "Спасибо, жду."
    },
    {
      "start": 283.02,
      "end": 283.82,
      "speaker": null,
      "text": "До свидания."
    }
  ]
}