{
  "file": "23.04.2026_10_06_40_+79254906780_m21_d131875_6.1776928000.mp3",
  "language": "ru",
  "language_probability": 1,
  "duration_seconds": 224.9,
  "segments": [
    {
      "start": 2.74,
      "end": 9.8,
      "speaker": null,
      "text": "Марин, доброе утро. Это Артем, у нас же компания «Мостэн». Мне передали Ваш телефон по поводу баннера, с вашим коллегами общались."
    },
    {
      "start": 10.56,
      "end": 10.78,
      "speaker": null,
      "text": "Да."
    },
    {
      "start": 12.76,
      "end": 17.46,
      "speaker": null,
      "text": "Я просто хотел уточнить, получается два баннера на одну конструкцию с турбометрическими?"
    },
    {
      "start": 18.15,
      "end": 20.07,
      "speaker": null,
      "text": "Один баннер, один."
    },
    {
      "start": 20.83,
      "end": 21.73,
      "speaker": null,
      "text": "Просто баннер, да?"
    },
    {
      "start": 22.11,
      "end": 25.47,
      "speaker": null,
      "text": "Один баннер, 2х3 метра, с подкипами."
    },
    {
      "start": 26.39,
      "end": 30.03,
      "speaker": null,
      "text": "Да-да-да, всё. Размеры мне уточнили после конструкции, мы сказали, да хорошо."
    },
    {
      "start": 30.03,
      "end": 31.01,
      "speaker": null,
      "text": "Да."
    },
    {
      "start": 31.95,
      "end": 36.29,
      "speaker": null,
      "text": "Как с вами дальнейший диалог? По номеру телефона, по почте?"
    },
    {
      "start": 36.99,
      "end": 43.23,
      "speaker": null,
      "text": "Я сейчас передам Наталье требование, как написать правильно."
    },
    {
      "start": 44.09,
      "end": 44.33,
      "speaker": null,
      "text": "Угу."
    },
    {
      "start": 44.65,
      "end": 50.05,
      "speaker": null,
      "text": "Чтобы она будет вам писать, вы счёт выставьте, посчитайте правильно, выставьте её счёт."
    },
    {
      "start": 50.25,
      "end": 50.57,
      "speaker": null,
      "text": "Хорошо."
    },
    {
      "start": 50.73,
      "end": 56.71,
      "speaker": null,
      "text": "Сейчас мы решим ещё по поводу цветопроба, как вы привезёте или у нас водитель приедет, заберёт её."
    },
    {
      "start": 56.95,
      "end": 58.33,
      "speaker": null,
      "text": "Угу. Всё, понял."
    },
    {
      "start": 58.33,
      "end": 63.13,
      "speaker": null,
      "text": "Ещё такой вопрос, я вчера забыла спросить. Профиль у вас какой используется?"
    },
    {
      "start": 64.14,
      "end": 65.92,
      "speaker": null,
      "text": "Вы имеете в печати баннера?"
    },
    {
      "start": 66.28,
      "end": 66.68,
      "speaker": null,
      "text": "Да."
    },
    {
      "start": 67.22,
      "end": 73.82,
      "speaker": null,
      "text": "Мы там без профиля печатаем, потому что под каждым невозможно подстроиться все печатки без профиля."
    },
    {
      "start": 74.39,
      "end": 76.55,
      "speaker": null,
      "text": "Потому что там конвейер у нас идёт."
    },
    {
      "start": 77.26,
      "end": 81.72,
      "speaker": null,
      "text": "То есть, если сейчас над конвейером намотка катушка баннера."
    },
    {
      "start": 96.2,
      "end": 97.22,
      "speaker": null,
      "text": "Угу."
    },
    {
      "start": 98.84,
      "end": 99.56,
      "speaker": null,
      "text": "Подкрутить сможете."
    },
    {
      "start": 99.56,
      "end": 99.6,
      "speaker": null,
      "text": "То есть, подкрутить сможете."
    },
    {
      "start": 99.76,
      "end": 104.8,
      "speaker": null,
      "text": "Дело в том, что баннер красный, там, градиент…"
    },
    {
      "start": 105.94,
      "end": 106.38,
      "speaker": null,
      "text": "Угу."
    },
    {
      "start": 106.4,
      "end": 106.62,
      "speaker": null,
      "text": "Угу."
    },
    {
      "start": 121.74,
      "end": 136.48,
      "speaker": null,
      "text": "Не болит, я не болит, я не болит."
    },
    {
      "start": 138.93,
      "end": 139.45,
      "speaker": null,
      "text": "Угу."
    },
    {
      "start": 139.45,
      "end": 140.55,
      "speaker": null,
      "text": "Можем знать, как поступить."
    },
    {
      "start": 140.67,
      "end": 143.61,
      "speaker": null,
      "text": "У нас есть ссылка на все цвета."
    },
    {
      "start": 143.81,
      "end": 147.29,
      "speaker": null,
      "text": "Как там по снику можно выбрать какие цвета."
    },
    {
      "start": 147.29,
      "end": 148.31,
      "speaker": null,
      "text": "Просто у нас…"
    },
    {
      "start": 148.31,
      "end": 151.01,
      "speaker": null,
      "text": "Которые, которые у вас уже проверенные рабочие, правильно?"
    },
    {
      "start": 151.41,
      "end": 151.85,
      "speaker": null,
      "text": "Да, да."
    },
    {
      "start": 151.99,
      "end": 152.61,
      "speaker": null,
      "text": "У нас есть…"
    },
    {
      "start": 152.61,
      "end": 155.31,
      "speaker": null,
      "text": "Вот, допустим, мы когда клиентам направляем бриз на разработку макета,"
    },
    {
      "start": 155.51,
      "end": 158.29,
      "speaker": null,
      "text": "чтобы не придлился цветом, у нас есть ссылка на все цвета."
    },
    {
      "start": 158.43,
      "end": 160.11,
      "speaker": null,
      "text": "Ну, то есть, там, книги программированные."
    },
    {
      "start": 160.27,
      "end": 161.75,
      "speaker": null,
      "text": "Я могу вы направить её как-то…"
    },
    {
      "start": 161.75,
      "end": 162.31,
      "speaker": null,
      "text": "Как вы скажите?"
    },
    {
      "start": 162.37,
      "end": 164.47,
      "speaker": null,
      "text": "По номеру с телефона мессенджера или на почту?"
    },
    {
      "start": 167.9,
      "end": 168.3,
      "speaker": null,
      "text": "Ээээ…"
    },
    {
      "start": 168.3,
      "end": 170.76,
      "speaker": null,
      "text": "Мессенджер уже сейчас тоже здесь не работает."
    },
    {
      "start": 170.94,
      "end": 172.68,
      "speaker": null,
      "text": "Лучше, конечно, на почту заправить."
    },
    {
      "start": 172.72,
      "end": 173.9,
      "speaker": null,
      "text": "А вы можете вот Наталью…"
    },
    {
      "start": 173.9,
      "end": 174.92,
      "speaker": null,
      "text": "У вас есть её почта?"
    },
    {
      "start": 176.54,
      "end": 178.38,
      "speaker": null,
      "text": "Наталиса Дефис Дэн Собака Мэвру?"
    },
    {
      "start": 178.38,
      "end": 179.24,
      "speaker": null,
      "text": "Эээ…"
    },
    {
      "start": 180.77,
      "end": 181.03,
      "speaker": null,
      "text": "Нет."
    },
    {
      "start": 181.45,
      "end": 183.09,
      "speaker": null,
      "text": "Она лучше с этой почты пишет, что ли?"
    },
    {
      "start": 183.86,
      "end": 186.42,
      "speaker": null,
      "text": "Ну, у меня только это одна почта есть, у меня другой нету."
    },
    {
      "start": 187.87,
      "end": 188.97,
      "speaker": null,
      "text": "О, господи!"
    },
    {
      "start": 190.4,
      "end": 191.18,
      "speaker": null,
      "text": "Надо сработать почту…"
    },
    {
      "start": 191.18,
      "end": 191.58,
      "speaker": null,
      "text": "Есть…"
    },
    {
      "start": 191.58,
      "end": 192.62,
      "speaker": null,
      "text": "Есть ваша…"
    },
    {
      "start": 192.62,
      "end": 193.86,
      "speaker": null,
      "text": "Есть ваша…"
    },
    {
      "start": 193.86,
      "end": 194.7,
      "speaker": null,
      "text": "Есть моя…"
    },
    {
      "start": 195.42,
      "end": 195.68,
      "speaker": null,
      "text": "Зублицкая."
    },
    {
      "start": 195.98,
      "end": 196.22,
      "speaker": null,
      "text": "Да."
    },
    {
      "start": 196.62,
      "end": 198.66,
      "speaker": null,
      "text": "Вот она сохранилась в ГРЦС, которая…"
    },
    {
      "start": 200.2,
      "end": 200.82,
      "speaker": null,
      "text": "Вот на неё…"
    },
    {
      "start": 201.52,
      "end": 205.54,
      "speaker": null,
      "text": "Вот на неё направьте, потому что есть же лайнер как раз-таки…"
    },
    {
      "start": 205.54,
      "end": 207.5,
      "speaker": null,
      "text": "Давайте, я тогда направлю вам…"
    },
    {
      "start": 207.5,
      "end": 210.9,
      "speaker": null,
      "text": "Я сейчас посмотрю бакет, да, тогда попробую подогнать…"
    },
    {
      "start": 210.9,
      "end": 213.52,
      "speaker": null,
      "text": "Примеры светопроб я направлю вам тогда, как он…"
    },
    {
      "start": 213.52,
      "end": 214.9,
      "speaker": null,
      "text": "Ну, в принципе, выглядит…"
    },
    {
      "start": 215.12,
      "end": 215.76,
      "speaker": null,
      "text": "Да."
    },
    {
      "start": 215.86,
      "end": 217.4,
      "speaker": null,
      "text": "…примеры, что ли мы так направлю?"
    },
    {
      "start": 217.48,
      "end": 217.96,
      "speaker": null,
      "text": "Обязательно."
    },
    {
      "start": 218.56,
      "end": 219.08,
      "speaker": null,
      "text": "Хорошо."
    },
    {
      "start": 219.44,
      "end": 220.12,
      "speaker": null,
      "text": "Тогда отправляйте."
    },
    {
      "start": 220.12,
      "end": 221.3,
      "speaker": null,
      "text": "Хорошо, попробую поправить."
    },
    {
      "start": 221.68,
      "end": 222.52,
      "speaker": null,
      "text": "Конечно, да."
    },
    {
      "start": 223.14,
      "end": 223.54,
      "speaker": null,
      "text": "Все, спасибо."
    }
  ]
}