{
  "file": "28.05.2026_16_14_13_79166725846_m49_d135299_e.1779974054.mp3",
  "language": "ru",
  "language_probability": 1,
  "duration_seconds": 103.3,
  "segments": [
    {
      "start": 0.18,
      "end": 1.5,
      "speaker": null,
      "text": "Елена, добрый день."
    },
    {
      "start": 1.82,
      "end": 3.24,
      "speaker": null,
      "text": "Да, Марьяна, добрый день."
    },
    {
      "start": 3.9,
      "end": 9.42,
      "speaker": null,
      "text": "Да, извините, Елена задержала вас, просто пара моментов, как тело я хотела так просто обсудить."
    },
    {
      "start": 9.88,
      "end": 18.34,
      "speaker": null,
      "text": "Адрес я помню, у нас сейчас заминка в том, что возможно его завтра не успеют привезти, а смогут привезти только в понедельник."
    },
    {
      "start": 18.36,
      "end": 25.68,
      "speaker": null,
      "text": "Это у нас получается уже 1 июня, он нам просто прям критично нужен, ну скажем так 3 июня."
    },
    {
      "start": 25.68,
      "end": 34.22,
      "speaker": null,
      "text": "Нет, у меня вопрос просто, я так понимаю, что он нужен, чтобы его померили, посмотрели правильно, чтобы мерки были точные, чтобы не было накладок размерами и прочее, да?"
    },
    {
      "start": 34.72,
      "end": 41.84,
      "speaker": null,
      "text": "Просто после того, как его посмотрят, мы сможем, если что, забрать его, ну грубо говоря, там сразу или не сразу обратно?"
    },
    {
      "start": 42.04,
      "end": 43.64,
      "speaker": null,
      "text": "Ну да, давайте так же делаем."
    },
    {
      "start": 44.46,
      "end": 51.74,
      "speaker": null,
      "text": "Да, чтобы мне просто понимать, насколько он там физически нужен, то есть если что, мы уже его сейчас как-то там с порванным чехлом заберём на конференцию."
    },
    {
      "start": 52.4,
      "end": 62.6,
      "speaker": null,
      "text": "Просто чтобы, он собственно так и ездил у нас, просто боялись, что там что-нибудь вывалится из него, а как бы уже новый подождём, просто дальше у нас там тоже следом одно за другим."
    },
    {
      "start": 63.06,
      "end": 66.84,
      "speaker": null,
      "text": "То есть так мы можем, если сделать, если завтра вдруг они не успеют доставить."
    },
    {
      "start": 66.92,
      "end": 67.74,
      "speaker": null,
      "text": "Да, да."
    },
    {
      "start": 67.74,
      "end": 76.36,
      "speaker": null,
      "text": "А то у нас там просто пока из тех, кто могут привозить это всякие вздеки и кайфи, они вроде обычно там прям день в день не довозят."
    },
    {
      "start": 76.48,
      "end": 79.32,
      "speaker": null,
      "text": "Это же сегодня уже полпятого, поэтому как-то да."
    },
    {
      "start": 79.72,
      "end": 87.02,
      "speaker": null,
      "text": "Ладно, Елена, я тогда сейчас уточню у логиста, что у нас там выходит, отпишусь вам, но наверное тогда счёт можно уже в любом случае установить, что нам понадобится."
    },
    {
      "start": 87.06,
      "end": 87.22,
      "speaker": null,
      "text": "Да."
    },
    {
      "start": 87.84,
      "end": 95.58,
      "speaker": null,
      "text": "Ну он Елена будет прям такой же, как бы, как был со всеми этими штуками-ставками, ну то есть в общем идентичный, которым он лежал."
    },
    {
      "start": 95.7,
      "end": 95.9,
      "speaker": null,
      "text": "Ага."
    },
    {
      "start": 96.38,
      "end": 97.64,
      "speaker": null,
      "text": "Всё, ладно, хорошо."
    },
    {
      "start": 97.94,
      "end": 99.9,
      "speaker": null,
      "text": "Ему тогда счёт, а из этого напишу."
    },
    {
      "start": 99.96,
      "end": 100.28,
      "speaker": null,
      "text": "Спасибо."
    },
    {
      "start": 100.58,
      "end": 101.3,
      "speaker": null,
      "text": "До свидания."
    },
    {
      "start": 102.21,
      "end": 102.75,
      "speaker": null,
      "text": "Всего доброго."
    }
  ]
}